src/__init__.py
src/client.py
src/launcher.py
src/server.py
chatexampy-0.1.dist-info/METADATA
chatexampy-0.1.dist-info/WHEEL
chatexampy-0.1.dist-info/top_level.txt
chatexampy-0.1.dist-info/RECORD
