Metadata-Version: 2.1
Name: chatexampy
Version: 0.1
Summary: example chat
Author: Liuba Kundas
Author-email: kundasl1@gmail.com
